pvl/__init__.py
pvl/collections.py
pvl/decoder.py
pvl/encoder.py
pvl/exceptions.py
pvl/grammar.py
pvl/lexer.py
pvl/new.py
pvl/parser.py
pvl/pvl_translate.py
pvl/pvl_validate.py
pvl/token.py
pvl-1.3.2.dist-info/AUTHORS.rst
pvl-1.3.2.dist-info/LICENSE
pvl-1.3.2.dist-info/METADATA
pvl-1.3.2.dist-info/WHEEL
pvl-1.3.2.dist-info/entry_points.txt
pvl-1.3.2.dist-info/top_level.txt
pvl-1.3.2.dist-info/RECORD
