Metadata-Version: 2.1
Name: pvl
Version: 1.3.2
Summary: Python implementation for PVL (Parameter Value Language) parsing and encoding.
Home-page: https://github.com/planetarypy/pvl
Author: The PlanetaryPy Developers
Maintainer: Ross Beyer
Maintainer-email: rbeyer@rossbeyer.net
License: BSD
Keywords: pvl
Platform: UNKNOWN
Classifier: Development Status :: 5 - Production/Stable
Classifier: Intended Audience :: Developers
Classifier: Intended Audience :: Science/Research
Classifier: License :: OSI Approved :: BSD License
Classifier: Natural Language :: English
Classifier: Programming Language :: Python :: 3.6
Classifier: Programming Language :: Python :: 3.7
Classifier: Programming Language :: Python :: 3.8
Classifier: Topic :: Text Processing
Provides-Extra: quantities
Provides-Extra: multidict
Provides-Extra: dateutil
Provides-Extra: allopts
